setup.cfg
setup.py
tensorairspace/__init__.py
tensorairspace/utils.py
tensorairspace.egg-info/PKG-INFO
tensorairspace.egg-info/SOURCES.txt
tensorairspace.egg-info/dependency_links.txt
tensorairspace.egg-info/requires.txt
tensorairspace.egg-info/top_level.txt