Metadata-Version: 2.1
Name: tensorairspace
Version: 0.1.1
Summary: TensorAeroSpace! - RL for Aerospace.
Home-page: https://github.com/TensorAirSpace/TensorAirSpace
Author-email: mr8bit@yandex.ru
Keywords: reinforcement-learning machine-learning gym openai aerospace toolbox python data-science
Requires-Python: >=3.7
